{"v":"5.4.4","fr":25,"ip":0,"op":29,"w":56,"h":68,"nm":"下拉刷新","ddd":0,"assets":[],"layers":[{"ddd":0,"ind":1,"ty":4,"nm":"“图层 2”轮廓","sr":1,"ks":{"o":{"a":0,"k":100,"ix":11},"r":{"a":0,"k":0,"ix":10},"p":{"a":0,"k":[27.82,27.323,0],"ix":2},"a":{"a":0,"k":[22.817,22.751,0],"ix":1},"s":{"a":0,"k":[100,100,100],"ix":6}},"ao":0,"shapes":[{"ty":"gr","it":[{"ind":0,"ty":"sh","ix":1,"ks":{"a":0,"k":{"i":[[4.083,-0.177],[1.439,2.412],[-1.44,2.41],[-2.805,-0.123],[0.001,-4.088]],"o":[[-2.805,0.122],[-1.438,-2.411],[1.44,-2.411],[4.083,0.18],[-0.002,4.087]],"v":[[0.511,7.63],[-6.379,3.913],[-6.376,-3.915],[0.516,-7.629],[7.816,0.003]],"c":true},"ix":2},"nm":"路径 1","mn":"ADBE Vector Shape - Group","hd":false},{"ty":"st","c":{"a":0,"k":[0.2,0.2,0.2,1],"ix":3},"o":{"a":0,"k":100,"ix":4},"w":{"a":0,"k":6,"ix":5},"lc":2,"lj":1,"ml":10,"bm":0,"nm":"描边 1","mn":"ADBE Vector Graphic - Stroke","hd":false},{"ty":"tr","p":{"a":0,"k":[22.817,22.751],"ix":2},"a":{"a":0,"k":[0,0],"ix":1},"s":{"a":0,"k":[100,100],"ix":3},"r":{"a":0,"k":0,"ix":6},"o":{"a":0,"k":100,"ix":7},"sk":{"a":0,"k":0,"ix":4},"sa":{"a":0,"k":0,"ix":5},"nm":"变换"}],"nm":"组 1","np":2,"cix":2,"bm":0,"ix":1,"mn":"ADBE Vector Group","hd":false},{"ty":"tm","s":{"a":0,"k":0,"ix":1},"e":{"a":1,"k":[{"i":{"x":[0.667],"y":[1]},"o":{"x":[0.333],"y":[0]},"t":0,"s":[0],"e":[100]},{"t":19}],"ix":2},"o":{"a":1,"k":[{"i":{"x":[0.667],"y":[1]},"o":{"x":[0.333],"y":[0]},"t":0,"s":[0],"e":[360]},{"t":19}],"ix":3},"m":1,"ix":2,"nm":"修剪路径 1","mn":"ADBE Vector Filter - Trim","hd":false}],"ip":0,"op":29,"st":0,"bm":0},{"ddd":0,"ind":2,"ty":4,"nm":"“图层 3”轮廓","sr":1,"ks":{"o":{"a":0,"k":100,"ix":11},"r":{"a":0,"k":0,"ix":10},"p":{"a":0,"k":[27.465,33.998,0],"ix":2},"a":{"a":0,"k":[39.538,43.802,0],"ix":1},"s":{"a":0,"k":[100,100,100],"ix":6}},"ao":0,"shapes":[{"ty":"gr","it":[{"ind":0,"ty":"sh","ix":1,"ks":{"a":0,"k":{"i":[[0,0],[0.003,7.014],[13.254,-0.005],[4.284,-7.355],[-4.29,-7.353],[-1.844,-1.641],[0,0],[-3.359,0],[0,0],[1.68,2.881]],"o":[[4.878,-4.353],[-0.005,-13.126],[-8.575,0.004],[-4.285,7.356],[1.277,2.188],[0,0],[-1.679,2.881],[0,0],[3.358,0],[0,0]],"v":[[16.591,12.63],[24.535,-5.038],[0.527,-28.798],[-20.253,-16.907],[-20.245,6.861],[-15.505,12.604],[-21.17,22.32],[-17.391,28.803],[18.462,28.803],[22.24,22.32]],"c":true},"ix":2},"nm":"路径 1","mn":"ADBE Vector Shape - Group","hd":false},{"ty":"st","c":{"a":0,"k":[0.2,0.2,0.2,1],"ix":3},"o":{"a":0,"k":100,"ix":4},"w":{"a":0,"k":6,"ix":5},"lc":2,"lj":1,"ml":10,"bm":0,"nm":"描边 1","mn":"ADBE Vector Graphic - Stroke","hd":false},{"ty":"tr","p":{"a":0,"k":[39.538,43.802],"ix":2},"a":{"a":0,"k":[0,0],"ix":1},"s":{"a":0,"k":[100,100],"ix":3},"r":{"a":0,"k":0,"ix":6},"o":{"a":0,"k":100,"ix":7},"sk":{"a":0,"k":0,"ix":4},"sa":{"a":0,"k":0,"ix":5},"nm":"变换"}],"nm":"组 1","np":2,"cix":2,"bm":0,"ix":1,"mn":"ADBE Vector Group","hd":false},{"ty":"tm","s":{"a":1,"k":[{"i":{"x":[0.667],"y":[1]},"o":{"x":[0.333],"y":[0]},"t":0,"s":[100],"e":[0]},{"t":28}],"ix":1},"e":{"a":0,"k":100,"ix":2},"o":{"a":1,"k":[{"i":{"x":[0.667],"y":[1]},"o":{"x":[0.333],"y":[0]},"t":0,"s":[0],"e":[-360]},{"t":28}],"ix":3},"m":1,"ix":2,"nm":"修剪路径 1","mn":"ADBE Vector Filter - Trim","hd":false}],"ip":0,"op":29,"st":0,"bm":0}],"markers":[]}